emdantic/__init__.py
emdantic/base.py
emdantic-0.1.0.dist-info/LICENSE
emdantic-0.1.0.dist-info/METADATA
emdantic-0.1.0.dist-info/WHEEL
emdantic-0.1.0.dist-info/RECORD
