Metadata-Version: 2.1
Name: emdantic
Version: 0.1.0
Summary: Embed pydantic models
License: MIT
Author: Patrick Barker
Author-email: patrickbarkerco@gmail.com
Requires-Python: >=3.10,<4.0
Classifier: License :: OSI Approved :: MIT License
Classifier: Programming Language :: Python :: 3
Classifier: Programming Language :: Python :: 3.10
Classifier: Programming Language :: Python :: 3.11
Classifier: Programming Language :: Python :: 3.12
Requires-Dist: pydantic (>=2.9.2,<3.0.0)
